luigi_tasks/__init__.py
luigi_tasks/tasks/__init__.py
luigi_tasks/tasks/tasks.py
luigi_tasks-0.1.3.dist-info/METADATA
luigi_tasks-0.1.3.dist-info/WHEEL
luigi_tasks-0.1.3.dist-info/entry_points.txt
luigi_tasks-0.1.3.dist-info/RECORD
