Metadata-Version: 2.4
Name: luigi-tasks
Version: 0.1.3
Summary: A collection of Luigi tasks for data processing
Author-email: urstrulyrohans <urstrulyrohansd@gmail.com>
Requires-Python: >=3.11
Requires-Dist: luigi===3.5.1
Provides-Extra: dev
Requires-Dist: build; extra == 'dev'
Requires-Dist: pytest; extra == 'dev'
Requires-Dist: twine; extra == 'dev'
